mcp_git_config/__init__.py
mcp_git_config/__main__.py
mcp_git_config/server.py
mcp_git_config-1.1.0.dist-info/METADATA
mcp_git_config-1.1.0.dist-info/WHEEL
mcp_git_config-1.1.0.dist-info/entry_points.txt
mcp_git_config-1.1.0.dist-info/licenses/LICENSE
mcp_git_config-1.1.0.dist-info/RECORD
