Metadata-Version: 2.4
Name: mcp-git-config
Version: 1.1.0
Summary: MCP server for Git repository detection and username retrieval
Project-URL: Homepage, https://github.com/shizeying/mcp-git-config
Project-URL: Repository, https://github.com/shizeying/mcp-git-config
Project-URL: Issues, https://github.com/shizeying/mcp-git-config/issues
Author-email: shizeying <w741069229@163.com>
License: MIT License
License-File: LICENSE
Keywords: git,mcp,model-context-protocol,server
Classifier: Development Status :: 5 - Production/Stable
Classifier: Intended Audience :: Developers
Classifier: License :: OSI Approved :: MIT License
Classifier: Programming Language :: Python :: 3
Classifier: Programming Language :: Python :: 3.10
Classifier: Programming Language :: Python :: 3.11
Classifier: Programming Language :: Python :: 3.12
Classifier: Topic :: Software Development :: Libraries :: Python Modules
Classifier: Topic :: Software Development :: Version Control :: Git
Requires-Python: >=3.10
Requires-Dist: mcp>=1.0.0
Provides-Extra: dev
Requires-Dist: mypy>=1.0.0; extra == 'dev'
Requires-Dist: pre-commit>=3.0.0; extra == 'dev'
Requires-Dist: pytest-asyncio; extra == 'dev'
Requires-Dist: pytest>=6.0; extra == 'dev'
Requires-Dist: ruff>=0.1.0; extra == 'dev'
